psychopass/__init__.py
psychopass/flowerpass.py
psychopass/psychopass.py
psychopass-0.2.1.dist-info/DESCRIPTION.rst
psychopass-0.2.1.dist-info/METADATA
psychopass-0.2.1.dist-info/RECORD
psychopass-0.2.1.dist-info/WHEEL
psychopass-0.2.1.dist-info/entry_points.txt
psychopass-0.2.1.dist-info/metadata.json
psychopass-0.2.1.dist-info/top_level.txt
